zimbabwean_id_number_validator/__init__.py
zimbabwean_id_number_validator/constants.py
zimbabwean_id_number_validator/validator.py
zimbabwean_id_number_validator-1.2.0.dist-info/METADATA
zimbabwean_id_number_validator-1.2.0.dist-info/WHEEL
zimbabwean_id_number_validator-1.2.0.dist-info/top_level.txt
zimbabwean_id_number_validator-1.2.0.dist-info/RECORD
