Metadata-Version: 2.2
Name: zimbabwean_id_number_validator
Version: 1.2.0
Summary: Zimbabwean national id number validator
Home-page: 
Author: Wellington Mpofu
Author-email: wellington.t.mpofu@gmail.com
Classifier: Programming Language :: Python :: 3
Classifier: License :: OSI Approved :: MIT License
Classifier: Operating System :: OS Independent
Requires-Python: >=3.6
Dynamic: author
Dynamic: author-email
Dynamic: classifier
Dynamic: description
Dynamic: description-content-type
Dynamic: requires-python
Dynamic: summary
